[{"style":"style3","imagePath":"images/89.jpg","pdfPath":"pdf/20161229%EF%BD%9C%E9%BB%83%E5%9C%8B%E6%98%8C%EF%BD%9C%E4%BA%A4%E9%80%9A%E5%A7%94%E5%93%A1%E6%9C%83%EF%BD%9C%E6%88%91%E5%9C%8B%E9%85%92%E5%BE%8C%E9%A7%95%E8%BB%8A%E7%8F%BE%E6%B3%81%E6%9A%A8%E9%98%B2%E5%88%B6%E4%BD%9C%E7%82%BA.pdf","title":"交通委員會","body":"20161229｜黃國昌｜交通委員會｜我國酒後駕車現況暨防制作為"},{"style":"style1","imagePath":"images/88.jpg","pdfPath":"pdf/20161228%EF%BD%9C%E9%BB%83%E5%9C%8B%E6%98%8C%EF%BD%9C%E5%85%A7%E6%94%BF%E5%A7%94%E5%93%A1%E6%9C%83%EF%BD%9C%E8%87%BA%E7%81%A3%E8%88%87%E6%BE%B3%E9%96%80%E9%81%BF%E5%85%8D%E8%88%AA%E7%A9%BA%E4%BC%81%E6%A5%AD%E9%9B%99%E9%87%8D%E8%AA%B2%E7%A8%85%E5%8D%94%E8%AD%B0.pdf","title":"內政委員會","body":"20161228｜黃國昌｜內政委員會｜臺灣與澳門避免航空企業雙重課稅協議"},{"style":"style5","imagePath":"images/87.jpg","pdfPath":"pdf/20161228%EF%BD%9C%E9%BB%83%E5%9C%8B%E6%98%8C%EF%BD%9C%E8%B2%A1%E6%94%BF%E5%A7%94%E5%93%A1%E6%9C%83%EF%BD%9C%E5%B9%B4%E9%87%91%E6%94%B9%E9%9D%A9%E8%88%87%E7%B4%8D%E7%A8%85%E8%80%85%E6%AC%8A%E5%88%A9%E4%BF%9D%E8%AD%B7.pdf","title":"財政委員會","body":"20161228｜黃國昌｜財政委員會｜年金改革與納稅者權利保護"},{"style":"style6","imagePath":"images/86.jpg","pdfPath":"pdf/20161226%EF%BD%9C%E9%BB%83%E5%9C%8B%E6%98%8C%EF%BD%9C%E8%B2%A1%E6%94%BF%E5%A7%94%E5%93%A1%E6%9C%83%EF%BD%9C%E7%A8%85%E6%8D%90%E7%A8%BD%E5%BE%B5%E6%B3%95%E4%B9%8B%E4%BF%AE%E6%AD%A3.pdf","title":"財政委員會","body":"20161226｜黃國昌｜財政委員會｜稅捐稽徵法之修正"},{"style":"style4","imagePath":"images/85.jpg","pdfPath":"pdf/20161222%EF%BD%9C%E9%BB%83%E5%9C%8B%E6%98%8C%EF%BD%9C%E7%A4%BE%E7%A6%8F%E8%A1%9B%E7%92%B0%E5%A7%94%E5%93%A1%E6%9C%83%EF%BD%9C%E5%8B%9E%E8%B3%87%E7%88%AD%E8%AD%B0%E8%99%95%E7%90%86%E6%B3%95%E3%80%81%E4%B8%8D%E7%95%B6%E5%8B%9E%E5%8B%95%E8%A1%8C%E7%82%BA%E3%80%81%E8%B2%AC%E4%BB%BB%E5%88%B6%E6%9C%89%E4%BC%91%E6%81%AF%E6%97%A5.pdf","title":"社福衛環委員會","body":"20161222｜黃國昌｜社福衛環委員會｜勞資爭議處理法、不當勞動行為、責任制有休息日"},{"style":"style1","imagePath":"images/84.jpg","pdfPath":"pdf/20161222%EF%BD%9C%E9%BB%83%E5%9C%8B%E6%98%8C%EF%BD%9C%E8%B2%A1%E6%94%BF%E5%A7%94%E5%93%A1%E6%9C%83%EF%BD%9C%E8%B2%A1%E6%94%BF%E6%94%B6%E6%94%AF%E5%8A%83%E5%88%86%E5%8F%8A%E8%A3%9C%E5%8A%A9.pdf","title":"財政委員會","body":"20161222｜黃國昌｜財政委員會｜財政收支劃分及補助"},{"style":"style2","imagePath":"images/83.jpg","pdfPath":"pdf/20161219%EF%BD%9C%E9%BB%83%E5%9C%8B%E6%98%8C%EF%BD%9C%E5%8F%B8%E6%B3%95%E6%B3%95%E5%88%B6%E5%A7%94%E5%93%A1%E6%9C%83%EF%BD%9C%E6%B0%91%E4%BA%8B%E8%A8%B4%E8%A8%9F%E6%B3%95%E4%B9%8B%E4%BF%AE%E6%AD%A3%E3%80%81%E6%B3%95%E5%AD%B8%E6%95%99%E5%AE%A4.pdf","title":"司法法制委員會","body":"20161219｜黃國昌｜司法法制委員會｜民事訴訟法之修正、法學教室"},{"style":"style3","imagePath":"images/82.jpg","pdfPath":"pdf/20161214%EF%BD%9C%E9%BB%83%E5%9C%8B%E6%98%8C%EF%BD%9C%E8%B2%A1%E6%94%BF%E5%A7%94%E5%93%A1%E6%9C%83%EF%BD%9C%E8%B2%A1%E6%94%BF%E9%83%A8%E6%89%80%E5%B1%AC%E9%87%91%E8%9E%8D%E6%A9%9F%E6%A7%8B%E9%A0%90%E7%AE%97.pdf","title":"財政委員會","body":"20161214｜黃國昌｜財政委員會｜財政部所屬金融機構預算"},{"style":"style4","imagePath":"images/81.jpg","pdfPath":"pdf/20161212%EF%BD%9C%E9%BB%83%E5%9C%8B%E6%98%8C%EF%BD%9C%E5%85%A7%E6%94%BF%E5%A7%94%E5%93%A1%E6%9C%83%EF%BD%9C%E9%9D%92%E5%B0%91%E5%B9%B4%E6%AF%92%E5%93%81%E5%95%8F%E9%A1%8C.pdf","title":"內政委員會","body":"20161212｜黃國昌｜內政委員會｜青少年毒品問題"},{"style":"style5","imagePath":"images/80.jpg","pdfPath":"pdf/20161212%EF%BD%9C%E9%BB%83%E5%9C%8B%E6%98%8C%EF%BD%9C%E8%B2%A1%E6%94%BF%E5%A7%94%E5%93%A1%E6%9C%83%EF%BD%9C%E6%B5%B7%E9%97%9C%E7%B7%9D%E6%AF%92%E5%8F%8A%E8%BC%BB%E5%B0%84%E6%AA%A2%E6%B8%AC.pdf","title":"財政委員會","body":"20161212｜黃國昌｜財政委員會｜海關緝毒及輻射檢測"},{"style":"style6","imagePath":"images/79.jpg","pdfPath":"pdf/20161208%EF%BD%9C%E9%BB%83%E5%9C%8B%E6%98%8C%EF%BD%9C%E8%B2%A1%E6%94%BF%E5%A7%94%E5%93%A1%E6%9C%83%EF%BD%9CRegulatory%20Sandbox%20&%20TRF.pdf","title":"財政委員會","body":"20161208｜黃國昌｜財政委員會｜Regulatory Sandbox &amp; TRF"},{"style":"style2","imagePath":"images/78.jpg","pdfPath":"pdf/20161205%EF%BD%9C%E9%BB%83%E5%9C%8B%E6%98%8C%EF%BD%9C%E5%8F%B8%E6%B3%95%E6%B3%95%E5%88%B6%E5%A7%94%E5%93%A1%E6%9C%83%EF%BD%9C%E6%B0%91%E4%BA%8B%E8%A8%B4%E8%A8%9F%E6%B3%95%E4%B9%8B%E4%BF%AE%E6%AD%A3%E3%80%81%E6%B3%95%E5%AD%B8%E6%95%99%E5%AE%A4.pdf","title":"司法法制委員會","body":"20161205｜黃國昌｜司法法制委員會｜民事訴訟法之修正、法學教室"},{"style":"style3","imagePath":"images/77.jpg","pdfPath":"pdf/20161205%EF%BD%9C%E9%BB%83%E5%9C%8B%E6%98%8C%EF%BD%9C%E8%B2%A1%E6%94%BF%E5%A7%94%E5%93%A1%E6%9C%83%EF%BD%9C%E5%85%AC%E5%8F%B8%E5%82%B5%E3%80%81%E9%87%91%E8%9E%8D%E5%82%B5%E5%88%B8%E8%AD%89%E4%BA%A4%E7%A8%85%E7%B9%BC%E7%BA%8C%E5%81%9C%E5%BE%B5%E3%80%81%E7%95%B6%E6%B2%96%E9%99%8D%E4%BA%A4%E6%98%93%E7%A8%85.pdf","title":"財政委員會","body":"20161205｜黃國昌｜財政委員會｜公司債、金融債券證交稅繼續停徵、當沖降交易稅"},{"style":"style1","imagePath":"images/76.jpg","pdfPath":"pdf/20161201%EF%BD%9C%E9%BB%83%E5%9C%8B%E6%98%8C%EF%BD%9C%E8%B2%A1%E6%94%BF%E5%A7%94%E5%93%A1%E6%9C%83%EF%BD%9C%E5%9C%8B%E5%8B%99%E6%A9%9F%E8%A6%81%E8%B2%BB%E3%80%81%E4%B8%8D%E7%95%B6%E9%BB%A8%E7%94%A2.pdf","title":"財政委員會","body":"20161201｜黃國昌｜財政委員會｜國務機要費、不當黨產"},{"style":"style5","imagePath":"images/75.jpg","pdfPath":"pdf/20161130%EF%BD%9C%E9%BB%83%E5%9C%8B%E6%98%8C%EF%BD%9C%E8%B2%A1%E6%94%BF%E5%A7%94%E5%93%A1%E6%9C%83%EF%BD%9C%E7%95%B6%E5%9C%8B%E6%9C%89%E5%9C%9F%E5%9C%B0%E6%88%90%E7%82%BA%E5%BB%A2%E5%9C%9F%E7%9F%B3%E6%8E%A9%E5%9F%8B%E5%A0%B4%EF%BC%9F.pdf","title":"財政委員會","body":"20161130｜黃國昌｜財政委員會｜當國有土地成為廢土石掩埋場？"},{"style":"style6","imagePath":"images/74.jpg","pdfPath":"pdf/20161123%EF%BD%9C%E9%BB%83%E5%9C%8B%E6%98%8C%EF%BD%9C%E8%B2%A1%E6%94%BF%E5%A7%94%E5%93%A1%E6%9C%83%EF%BD%9C%E5%BE%A9%E8%88%88%E8%88%AA%E7%A9%BA%E5%81%9C%E8%88%AA%E3%80%81%E4%BA%A4%E6%98%93%E7%95%B0%E5%B8%B8.pdf","title":"財政委員會","body":"20161123｜黃國昌｜財政委員會｜復興航空停航、交易異常"},{"style":"style4","imagePath":"images/73.jpg","pdfPath":"pdf/20161121%EF%BD%9C%E9%BB%83%E5%9C%8B%E6%98%8C%EF%BD%9C%E6%95%99%E8%82%B2%E6%96%87%E5%8C%96%E5%A7%94%E5%93%A1%E6%9C%83%EF%BD%9C%E5%8F%B0%E5%A4%A7%E8%AB%96%E6%96%87%E9%80%A0%E5%81%87.pdf","title":"教育文化委員會","body":"20161121｜黃國昌｜教育文化委員會｜台大論文造假"},{"style":"style1","imagePath":"images/72.jpg","pdfPath":"pdf/20161121%EF%BD%9C%E9%BB%83%E5%9C%8B%E6%98%8C%EF%BD%9C%E5%8F%B8%E6%B3%95%E6%B3%95%E5%88%B6%E5%A7%94%E5%93%A1%E6%9C%83%EF%BD%9C%E5%B9%B4%E9%87%91%E6%94%B9%E9%9D%A9%E6%95%B4%E9%AB%94%E8%A6%8F%E5%8A%83%E9%85%8D%E5%A5%97.pdf","title":"司法法制委員會","body":"20161121｜黃國昌｜司法法制委員會｜年金改革整體規劃配套"},{"style":"style2","imagePath":"images/71.jpg","pdfPath":"pdf/20161121%EF%BD%9C%E9%BB%83%E5%9C%8B%E6%98%8C%EF%BD%9C%E8%B2%A1%E6%94%BF%E5%A7%94%E5%93%A1%E6%9C%83%EF%BD%9C%E9%87%91%E8%9E%8D%E6%B6%88%E8%B2%BB%E8%80%85%E4%BF%9D%E8%AD%B7%E6%B3%95.pdf","title":"財政委員會","body":"20161121｜黃國昌｜財政委員會｜金融消費者保護法"},{"style":"style3","imagePath":"images/70.jpg","pdfPath":"pdf/20161117%EF%BD%9C%E9%BB%83%E5%9C%8B%E6%98%8C%EF%BD%9C%E8%B2%A1%E6%94%BF%E5%A7%94%E5%93%A1%E6%9C%83%EF%BD%9C%E6%9C%83%E8%A8%88%E5%B8%AB%E6%B6%88%E6%A5%B5%E8%A6%81%E4%BB%B6%E3%80%81%E6%99%AE%E6%83%A0%E9%87%91%E8%9E%8D.pdf","title":"財政委員會","body":"20161117｜黃國昌｜財政委員會｜會計師消極要件、普惠金融"},{"style":"style4","imagePath":"images/69.jpg","pdfPath":"pdf/20161114%EF%BD%9C%E9%BB%83%E5%9C%8B%E6%98%8C%EF%BD%9C%E7%A4%BE%E7%A6%8F%E8%A1%9B%E7%92%B0%E5%A7%94%E5%93%A1%E6%9C%83%EF%BD%9C%E8%B3%AA%E8%A9%A2%E9%83%AD%E8%8A%B3%E7%85%9C%E4%B8%80%E4%BE%8B%E4%B8%80%E4%BC%91%E3%80%81%E4%B8%83%E5%A4%A9%E5%81%87.pdf","title":"社福衛環委員會","body":"20161114｜黃國昌｜社福衛環委員會｜質詢郭芳煜一例一休、七天假"},{"style":"style5","imagePath":"images/68.jpg","pdfPath":"pdf/20161114%EF%BD%9C%E9%BB%83%E5%9C%8B%E6%98%8C%EF%BD%9C%E5%8F%B8%E6%B3%95%E6%B3%95%E5%88%B6%E5%A7%94%E5%93%A1%E6%9C%83%EF%BD%9C%E4%BA%BA%E6%B0%91%E5%8F%83%E8%88%87%E5%AF%A9%E5%88%A4%E8%8D%89%E6%A1%88%E9%80%B2%E5%BA%A6%E3%80%81%E5%8B%9E%E5%8B%95%E7%89%B9%E5%88%A5%E7%A8%8B%E5%BA%8F%E6%B3%95.pdf","title":"司法法制委員會","body":"20161114｜黃國昌｜司法法制委員會｜人民參與審判草案進度、勞動特別程序法"},{"style":"style6","imagePath":"images/67.jpg","pdfPath":"pdf/20161114%EF%BD%9C%E9%BB%83%E5%9C%8B%E6%98%8C%EF%BD%9C%E8%B2%A1%E6%94%BF%E5%A7%94%E5%93%A1%E6%9C%83%EF%BD%9C%E7%84%A1%E6%B3%95%E6%BA%90%E7%9A%84%E7%A8%85%E5%8B%99%E4%BA%BA%E5%93%A1%E7%8D%8E%E5%8B%B5%E9%87%91%E3%80%81%E5%9C%B0%E5%83%B9%E7%A8%85%E3%80%81%E8%B2%A8%E7%89%A9%E7%A8%85.pdf","title":"財政委員會","body":"20161114｜黃國昌｜財政委員會｜無法源的稅務人員獎勵金、地價稅、貨物稅"},{"style":"style2","imagePath":"images/66.jpg","pdfPath":"pdf/20161110%EF%BD%9C%E9%BB%83%E5%9C%8B%E6%98%8C%EF%BD%9C%E8%B2%A1%E6%94%BF%E5%A7%94%E5%93%A1%E6%9C%83%EF%BD%9C%E6%A8%82%E9%99%9E%E6%A1%88%E3%80%81%E4%B8%AD%E5%9C%8B%E4%BF%A1%E8%A8%97%E3%80%81%E8%AD%89%E6%89%80%E7%A8%85.pdf","title":"財政委員會","body":"20161110｜黃國昌｜財政委員會｜樂陞案、中國信託、證所稅"},{"style":"style3","imagePath":"images/65.jpg","pdfPath":"pdf/20161109%EF%BD%9C%E9%BB%83%E5%9C%8B%E6%98%8C%EF%BD%9C%E6%95%99%E8%82%B2%E6%96%87%E5%8C%96%E5%A7%94%E5%93%A1%E6%9C%83%EF%BD%9C%E4%B8%AD%E7%A0%94%E9%99%A2%E3%80%81%E5%8F%B8%E6%B3%95%E6%94%B9%E9%9D%A9%E3%80%81%E5%8F%B8%E6%B3%95%E5%88%B6%E5%BA%A6%E5%AF%A6%E8%AD%89%E7%A0%94%E7%A9%B6%E5%9F%BA%E7%A4%8E.pdf","title":"教育文化委員會","body":"20161109｜黃國昌｜教育文化委員會｜中研院、司法改革、司法制度實證研究基礎"},{"style":"style1","imagePath":"images/64.jpg","pdfPath":"pdf/20161109%EF%BD%9C%E9%BB%83%E5%9C%8B%E6%98%8C%EF%BD%9C%E8%B2%A1%E6%94%BF%E5%A7%94%E5%93%A1%E6%9C%83%EF%BD%9C%E8%B3%AA%E8%A9%A2%E5%A4%AE%E8%A1%8C%E5%BD%AD%E6%B7%AE%E5%8D%97.pdf","title":"財政委員會","body":"20161109｜黃國昌｜財政委員會｜質詢央行彭淮南"},{"style":"style5","imagePath":"images/63.jpg","pdfPath":"pdf/20161107%EF%BD%9C%E9%BB%83%E5%9C%8B%E6%98%8C%EF%BD%9C%E7%B6%93%E6%BF%9F%E5%A7%94%E5%93%A1%E6%9C%83%EF%BD%9C%E6%A0%B8%E5%9B%9B%E5%B0%81%E5%AD%98%E3%80%81%E8%A8%AD%E5%82%99%E7%B6%AD%E8%AD%B7%E7%AE%A1%E7%90%86%E9%A0%90%E7%AE%97%2020%E5%84%84%20%E3%80%8C%E7%A0%B4%E9%8A%85%E7%88%9B%E9%90%B5%E3%80%8D%20%E8%B3%87%E7%94%A2%E8%99%95%E5%88%86%E8%A8%88%E7%95%AB.pdf","title":"經濟委員會","body":"20161107｜黃國昌｜經濟委員會｜核四封存、設備維護管理預算 20億 「破銅爛鐵」 資產處分計畫"},{"style":"style6","imagePath":"images/62.jpg","pdfPath":"pdf/20161107%EF%BD%9C%E9%BB%83%E5%9C%8B%E6%98%8C%EF%BD%9C%E8%B2%A1%E6%94%BF%E5%A7%94%E5%93%A1%E6%9C%83%EF%BD%9C%E5%9C%8B%E6%9C%89%E8%B2%A1%E7%94%A2%E9%81%AD%E6%AC%8A%E8%B2%B4%E6%8E%A0%E5%A5%AA%E7%9B%B8%E9%97%9C%E4%BD%9C%E7%82%BA.pdf","title":"財政委員會","body":"20161107｜黃國昌｜財政委員會｜國有財產遭權貴掠奪相關作為"},{"style":"style4","imagePath":"images/61.jpg","pdfPath":"pdf/20161103%EF%BD%9C%E9%BB%83%E5%9C%8B%E6%98%8C%EF%BD%9C%E8%B2%A1%E6%94%BF%E5%A7%94%E5%93%A1%E6%9C%83%EF%BD%9C%E5%85%AC%E7%9B%8A%E5%BD%A9%E5%88%B8.pdf","title":"財政委員會","body":"20161103｜黃國昌｜財政委員會｜公益彩券"},{"style":"style1","imagePath":"images/60.jpg","pdfPath":"pdf/20161102%EF%BD%9C%E9%BB%83%E5%9C%8B%E6%98%8C%EF%BD%9C%E7%A4%BE%E7%A6%8F%E8%A1%9B%E7%92%B0%E5%A7%94%E5%93%A1%E6%9C%83%EF%BD%9C%E9%81%A0%E9%9B%84%E9%86%AB%E7%99%82%E5%9C%92%E5%8D%80.pdf","title":"社福衛環委員會","body":"20161102｜黃國昌｜社福衛環委員會｜遠雄醫療園區"},{"style":"style2","imagePath":"images/59.jpg","pdfPath":"pdf/20161102%EF%BD%9C%E9%BB%83%E5%9C%8B%E6%98%8C%EF%BD%9C%E8%B2%A1%E6%94%BF%E5%A7%94%E5%93%A1%E6%9C%83%EF%BD%9C%E5%85%86%E8%B1%90%E6%A1%88%E3%80%81%E9%81%A0%E9%9B%84%E9%86%AB%E7%99%82%E5%9C%92%E5%8D%80%E3%80%81%E7%94%A2%E6%A5%AD%E5%89%B5%E6%96%B0%E6%A2%9D%E4%BE%8B%E3%80%81%E4%BC%81%E6%A5%AD%E7%A7%9F%E7%A8%85%E5%84%AA%E6%83%A0.pdf","title":"財政委員會","body":"20161102｜黃國昌｜財政委員會｜兆豐案、遠雄醫療園區、產業創新條例、企業租稅優惠"},{"style":"style3","imagePath":"images/58.jpg","pdfPath":"pdf/20161031%EF%BD%9C%E9%BB%83%E5%9C%8B%E6%98%8C%EF%BD%9C%E8%B2%A1%E6%94%BF%E5%A7%94%E5%93%A1%E6%9C%83%EF%BD%9C%E5%85%AC%E5%8B%99%E4%BA%BA%E5%93%A1%E6%85%B0%E5%95%8F%E9%87%91%E3%80%81%E7%B8%BE%E6%95%88%E5%AF%A9%E8%A8%88%E5%A0%B1%E5%91%8A%E5%AF%A6%E6%95%88%E3%80%81%E7%92%B0%E5%A2%83%E5%AF%A9%E8%A8%88.pdf","title":"財政委員會","body":"20161031｜黃國昌｜財政委員會｜公務人員慰問金、績效審計報告實效、環境審計"},{"style":"style4","imagePath":"images/57.jpg","pdfPath":"pdf/20161027%EF%BD%9C%E9%BB%83%E5%9C%8B%E6%98%8C%EF%BD%9C%E8%B2%A1%E6%94%BF%E5%A7%94%E5%93%A1%E6%9C%83%EF%BD%9C%E5%85%86%E8%B1%90%E6%A1%88.pdf","title":"財政委員會","body":"20161027｜黃國昌｜財政委員會｜兆豐案"},{"style":"style5","imagePath":"images/56.jpg","pdfPath":"pdf/20161026%EF%BD%9C%E9%BB%83%E5%9C%8B%E6%98%8C%EF%BD%9C%E5%8F%B8%E6%B3%95%E6%B3%95%E5%88%B6%E5%A7%94%E5%93%A1%E6%9C%83%EF%BD%9C%E6%B4%97%E9%8C%A2%E9%98%B2%E5%88%B6%E6%B3%95.pdf","title":"司法法制委員會","body":"20161026｜黃國昌｜司法法制委員會｜洗錢防制法"},{"style":"style6","imagePath":"images/55.jpg","pdfPath":"pdf/20161024%EF%BD%9C%E9%BB%83%E5%9C%8B%E6%98%8C%EF%BD%9C%E6%95%99%E8%82%B2%E6%96%87%E5%8C%96%E5%A7%94%E5%93%A1%E6%9C%83%EF%BD%9C%E6%A0%B8%E8%83%BD%E5%AE%89%E5%85%A8%E7%AE%A1%E5%88%B6%E6%A8%99%E6%BA%96%207%E6%9C%88%E9%96%93%E6%A0%B8%E4%BA%8C%E7%88%90%E5%BF%83%E7%87%83%E6%96%99%E7%A0%B4%E6%90%8D%E8%AD%A6%E5%A0%B1%E5%81%B5%E6%B8%AC.pdf","title":"教育文化委員會","body":"20161024｜黃國昌｜教育文化委員會｜核能安全管制標準 7月間核二爐心燃料破損警報偵測"},{"style":"style2","imagePath":"images/54.jpg","pdfPath":"pdf/20161024%EF%BD%9C%E9%BB%83%E5%9C%8B%E6%98%8C%EF%BD%9C%E8%B2%A1%E6%94%BF%E5%A7%94%E5%93%A1%E6%9C%83%EF%BD%9C%E7%A4%BE%E6%9C%83%E4%BD%8F%E5%AE%85%E3%80%81%E5%9F%BA%E9%9A%86%E6%B2%B3%E8%B0%B7%E5%BB%8A%E9%81%93%E3%80%81%E9%81%A0%E9%9B%84(%E9%86%AB%E7%99%82%E5%9C%92%E5%8D%80)%E3%80%81%E6%95%91%E5%9C%8B%E5%9C%98%E7%A7%9F%E7%B4%84(%E9%87%91%E5%B1%B1).pdf","title":"財政委員會","body":"20161024｜黃國昌｜財政委員會｜社會住宅、基隆河谷廊道、遠雄(醫療園區)、救國團租約(金山)"},{"style":"style3","imagePath":"images/53.jpg","pdfPath":"pdf/20161018%EF%BD%9C%E9%BB%83%E5%9C%8B%E6%98%8C%EF%BD%9C%E9%99%A2%E6%9C%83%EF%BD%9C%E6%B1%90%E6%AD%A2%E4%BA%A4%E9%80%9A%E3%80%81%E7%91%9E%E8%8A%B3%E5%8F%B0%E9%90%B5%E8%8A%B1%E5%8F%B0%E4%BD%94%E8%B7%AF%E9%9D%A2.pdf","title":"院會","body":"20161018｜黃國昌｜院會｜汐止交通、瑞芳台鐵花台佔路面"},{"style":"style1","imagePath":"images/52.jpg","pdfPath":"pdf/20161017%EF%BD%9C%E9%BB%83%E5%9C%8B%E6%98%8C%EF%BD%9C%E9%99%A2%E6%9C%83%EF%BD%9C%E5%AF%A9%E6%9F%A5%E5%8F%B8%E6%B3%95%E9%99%A2%E9%95%B7%E3%80%81%E5%A4%A7%E6%B3%95%E5%AE%98%E8%A2%AB%E6%8F%90%E5%90%8D%E4%BA%BA%20%E5%BC%B5%E7%93%8A%E6%96%87.pdf","title":"院會","body":"20161017｜黃國昌｜院會｜審查司法院長、大法官被提名人 張瓊文"},{"style":"style5","imagePath":"images/51.jpg","pdfPath":"pdf/20161013%EF%BD%9C%E9%BB%83%E5%9C%8B%E6%98%8C%EF%BD%9C%E9%99%A2%E6%9C%83%EF%BD%9C%E5%AF%A9%E6%9F%A5%E5%8F%B8%E6%B3%95%E9%99%A2%E9%95%B7%E3%80%81%E5%A4%A7%E6%B3%95%E5%AE%98%E8%A2%AB%E6%8F%90%E5%90%8D%E4%BA%BA%20%E8%94%A1%E7%82%AF%E7%87%89.pdf","title":"院會","body":"20161013｜黃國昌｜院會｜審查司法院長、大法官被提名人 蔡炯燉"},{"style":"style6","imagePath":"images/50.jpg","pdfPath":"pdf/20161013%EF%BD%9C%E9%BB%83%E5%9C%8B%E6%98%8C%EF%BD%9C%E9%99%A2%E6%9C%83%EF%BD%9C%E5%AF%A9%E6%9F%A5%E5%8F%B8%E6%B3%95%E9%99%A2%E9%95%B7%E3%80%81%E5%A4%A7%E6%B3%95%E5%AE%98%E8%A2%AB%E6%8F%90%E5%90%8D%E4%BA%BA%20%E8%A8%B1%E5%AE%97%E5%8A%9B%E3%80%81%E5%8F%B8%E6%B3%95%E9%99%A2%E4%BA%BA%E4%BA%8B%E5%90%8C%E6%84%8F%E6%AC%8A.pdf","title":"院會","body":"20161013｜黃國昌｜院會｜審查司法院長、大法官被提名人 許宗力"},{"style":"style4","imagePath":"images/49.jpg","pdfPath":"pdf/20161012%EF%BD%9C%E9%BB%83%E5%9C%8B%E6%98%8C%EF%BD%9C%E8%B2%A1%E6%94%BF%E5%A7%94%E5%93%A1%E6%9C%83%EF%BD%9C%E9%95%B7%E7%85%A7%E8%B2%A1%E6%BA%90%E3%80%81%E8%A1%9B%E7%A6%8F%E9%83%A8%E3%80%81%E8%8F%B8%E7%A8%85.pdf","title":"財政委員會","body":"20161012｜黃國昌｜財政委員會｜長照財源、衛福部、菸稅"},{"style":"style1","imagePath":"images/48.jpg","pdfPath":"pdf/20160929%EF%BD%9C%E9%BB%83%E5%9C%8B%E6%98%8C%EF%BD%9C%E4%BA%A4%E9%80%9A%E5%A7%94%E5%93%A1%E6%9C%83%EF%BD%9CNCC%E4%B8%AD%E5%98%89%E6%A1%88%E3%80%81%E9%81%A0%E5%82%B3%E3%80%81%E6%8A%95%E5%AF%A9%E6%9C%83.pdf","title":"交通委員會","body":"20160929｜黃國昌｜交通委員會｜NCC中嘉案、遠傳、投審會"},{"style":"style2","imagePath":"images/47.jpg","pdfPath":"pdf/20160929%EF%BD%9C%E9%BB%83%E5%9C%8B%E6%98%8C%EF%BD%9C%E8%B2%A1%E6%94%BF%E5%A7%94%E5%93%A1%E6%9C%83%EF%BD%9C%E7%99%BE%E5%B0%BA%E7%AB%BF%E9%A0%AD%E6%94%B6%E8%B3%BC%E6%A8%82%E9%99%9E.pdf","title":"財政委員會","body":"20160929｜黃國昌｜財政委員會｜百尺竿頭收購樂陞"},{"style":"style3","imagePath":"images/46.jpg","pdfPath":"pdf/20160926%EF%BD%9C%E9%BB%83%E5%9C%8B%E6%98%8C%EF%BD%9C%E9%99%A2%E6%9C%83%EF%BD%9C2017%E9%A0%90%E7%AE%97%E7%B7%A8%E5%88%B6%E3%80%81%E8%BB%8D%E5%85%AC%E6%95%99%E5%B9%B4%E7%B5%82%E6%85%B0%E5%95%8F%E9%87%91%E3%80%81%E6%A0%B8%E5%9B%9B%E5%B0%81%E5%AD%98.pdf","title":"院會","body":"20160926｜黃國昌｜院會｜2017預算編制、軍公教年終慰問金、核四封存"},{"style":"style4","imagePath":"images/45.jpg","pdfPath":"pdf/20160922%EF%BD%9C%E9%BB%83%E5%9C%8B%E6%98%8C%EF%BD%9C%E7%A4%BE%E7%A6%8F%E8%A1%9B%E7%92%B0%E5%A7%94%E5%93%A1%E6%9C%83%EF%BD%9C%E4%B8%83%E4%BC%91%E4%B8%80%E5%87%BD%E9%87%8B.pdf","title":"社福衛環委員會","body":"20160922｜黃國昌｜社福衛環委員會｜七休一函釋"},{"style":"style5","imagePath":"images/44.jpg","pdfPath":"pdf/20160922%EF%BD%9C%E9%BB%83%E5%9C%8B%E6%98%8C%EF%BD%9C%E8%B2%A1%E6%94%BF%E5%A7%94%E5%93%A1%E6%9C%83%EF%BD%9C%E5%85%AC%E8%82%A1%E9%87%8B%E8%82%A1%E3%80%81%E9%A0%90%E7%AE%97%E7%B7%A8%E8%A3%BD%E5%8E%9F%E5%89%87%E3%80%81%E5%AE%B6%E6%88%B6%E6%89%80%E5%BE%97%E7%B5%B1%E8%A8%88%E7%B5%84%E8%B7%9D%E5%86%8D%E7%B4%B0%E5%88%86.pdf","title":"財政委員會","body":"20160922｜黃國昌｜財政委員會｜公股釋股、預算編製原則、家戶所得統計組距再細分"},{"style":"style6","imagePath":"images/43.jpg","pdfPath":"pdf/20160921%EF%BD%9C%E9%BB%83%E5%9C%8B%E6%98%8C%EF%BD%9C%E8%B2%A1%E6%94%BF%E5%A7%94%E5%93%A1%E6%9C%83%EF%BD%9C%E5%85%86%E8%B1%90%E6%A1%88.pdf","title":"財政委員會","body":"20160921｜黃國昌｜財政委員會｜兆豐案"},{"style":"style2","imagePath":"images/42.jpg","pdfPath":"pdf/20160713%EF%BD%9C%E9%BB%83%E5%9C%8B%E6%98%8C%EF%BD%9C%E7%B6%93%E6%BF%9F%E5%A7%94%E5%93%A1%E6%9C%83%EF%BD%9C%E6%A0%B8%E4%B8%80%E5%BB%B6%E5%BD%B9%E7%94%B3%E8%AB%8B%E6%92%A4%E5%9B%9E%E3%80%81%E6%A0%B8%E9%9B%BB%E5%BB%A0%E9%98%B2%E7%81%BD.pdf","title":"經濟委員會","body":"20160713｜黃國昌｜經濟委員會｜核一延役申請撤回、核電廠防災"},{"style":"style3","imagePath":"images/41.jpg","pdfPath":"pdf/20160713%EF%BD%9C%E9%BB%83%E5%9C%8B%E6%98%8C%EF%BD%9C%E8%B2%A1%E6%94%BF%E5%A7%94%E5%93%A1%E6%9C%83%EF%BD%9C%E7%A6%81%E7%87%92%E7%94%9F%E7%85%A4%E7%9F%B3%E6%B2%B9%E7%84%A6%E4%B8%AD%E5%A4%AE%E6%B3%95%E4%BB%A4%E4%BF%AE%E6%94%B9%E9%85%8D%E5%A5%97.pdf","title":"財政委員會","body":"20160713｜黃國昌｜財政委員會｜禁燒生煤石油焦中央法令修改配套"},{"style":"style1","imagePath":"images/40.jpg","pdfPath":"pdf/20160711%EF%BD%9C%E9%BB%83%E5%9C%8B%E6%98%8C%EF%BD%9C%E8%B2%A1%E6%94%BF%E5%A7%94%E5%93%A1%E6%9C%83%EF%BD%9C%E8%B3%AA%E8%A9%A2%E5%9C%8B%E6%9C%89%E8%B2%A1%E7%94%A2%E7%BD%B2.pdf","title":"財政委員會","body":"20160711｜黃國昌｜財政委員會｜質詢國有財產署"},{"style":"style5","imagePath":"images/39.jpg","pdfPath":"pdf/20160707%EF%BD%9C%E9%BB%83%E5%9C%8B%E6%98%8C%EF%BD%9C%E7%A4%BE%E7%A6%8F%E8%A1%9B%E7%92%B0%E5%A7%94%E5%93%A1%E6%9C%83%EF%BD%9C%E9%9B%B2%E6%9E%97%E5%85%AD%E8%BC%95.pdf","title":"社福衛環委員會","body":"20160707｜黃國昌｜社福衛環委員會｜雲林六輕"},{"style":"style6","imagePath":"images/38.jpg","pdfPath":"pdf/20160706%EF%BD%9C%E9%BB%83%E5%9C%8B%E6%98%8C%EF%BD%9C%E7%A4%BE%E7%A6%8F%E8%A1%9B%E7%92%B0%E5%A7%94%E5%93%A1%E6%9C%83%EF%BD%9C%E5%A4%A7%E5%B0%88%E9%99%A2%E6%A0%A1%E5%85%BC%E4%BB%BB%E6%95%99%E5%B8%AB%E7%B4%8D%E5%85%A5%E5%8B%9E%E5%8B%95%E5%9F%BA%E6%BA%96%E6%B3%95%E5%85%B7%E9%AB%94%E6%99%82%E7%A8%8B.pdf","title":"社福衛環委員會","body":"20160706｜黃國昌｜社福衛環委員會｜大專院校兼任教師納入勞動基準法具體時程"},{"style":"style4","imagePath":"images/37.jpg","pdfPath":"pdf/20160704%EF%BD%9C%E9%BB%83%E5%9C%8B%E6%98%8C%EF%BD%9C%E8%B2%A1%E6%94%BF%E5%A7%94%E5%93%A1%E6%9C%83%EF%BD%9C%E7%B6%93%E6%BF%9F%E9%83%A8103%20%E5%B9%B4%E6%B1%BA%E7%AE%97%E5%A0%B1%E5%91%8A.pdf","title":"財政委員會","body":"20160704｜黃國昌｜財政委員會｜經濟部103 年決算報告"},{"style":"style1","imagePath":"images/36.jpg","pdfPath":"pdf/20160706%EF%BD%9C%E9%BB%83%E5%9C%8B%E6%98%8C%EF%BD%9C%E7%A4%BE%E7%A6%8F%E8%A1%9B%E7%92%B0%E5%A7%94%E5%93%A1%E6%9C%83%20%EF%BD%9C%E8%B3%AA%E8%A9%A2%E5%8B%9E%E5%8B%95%E9%83%A8%E9%95%B7%E9%83%AD%E8%8A%B3%E7%85%9C%EF%BC%9A%E9%80%B1%E4%BC%912%E6%97%A5%E6%8E%A1%E4%B8%80%E4%BE%8B%E4%B8%80%E4%BC%91%EF%BC%9F%EF%BC%81.pdf","title":"社福衛環委員會","body":"20160706｜黃國昌｜社福衛環委員會｜質詢勞動部長郭芳煜：週休2日採一例一休？！"},{"style":"style2","imagePath":"images/35.jpg","pdfPath":"pdf/20160615%EF%BD%9C%E9%BB%83%E5%9C%8B%E6%98%8C%EF%BD%9C%E4%BA%A4%E9%80%9A%E5%A7%94%E5%93%A1%E6%9C%83%EF%BD%9C%E8%8F%AF%E8%88%AA%E5%B7%A5%E6%9C%83%E4%B8%8D%E7%95%B6%E8%A7%A3%E9%9B%87%E3%80%81%E9%81%A0%E9%80%9A%E9%9B%BB%E6%94%B6%E7%BD%B0%E9%8D%B0.pdf","title":"交通委員會","body":"20160615｜黃國昌｜交通委員會｜華航工會不當解雇、遠通電收罰鍰"},{"style":"style3","imagePath":"images/34.jpg","pdfPath":"pdf/20160606%EF%BD%9C%E9%BB%83%E5%9C%8B%E6%98%8C%EF%BD%9C%E7%B6%93%E6%BF%9F%E5%A7%94%E5%93%A1%E6%9C%83%EF%BD%9C%20%E6%A0%B8%E4%B8%80%E5%BB%A0%E6%98%AF%E4%BD%B5%E8%81%AF%E4%B8%8D%E6%98%AF%E9%87%8D%E5%95%9F%EF%BC%9F%EF%BC%81.pdf","title":"經濟委員會","body":"20160606｜黃國昌｜經濟委員會｜ 核一廠是併聯不是重啟？！"},{"style":"style4","imagePath":"images/33.jpg","pdfPath":"pdf/20160603%EF%BD%9C%E9%BB%83%E5%9C%8B%E6%98%8C%EF%BD%9C%E9%99%A2%E6%9C%83%EF%BD%9C%20%E6%96%B0%E6%94%BF%E5%BA%9C%E9%A6%96%E5%BA%A6%E6%96%BD%E6%94%BF%E5%A0%B1%E5%91%8A.pdf","title":"院會","body":"20160603｜黃國昌｜院會｜ 新政府首度施政報告"},{"style":"style5","imagePath":"images/32.jpg","pdfPath":"pdf/20160512%EF%BD%9C%E9%BB%83%E5%9C%8B%E6%98%8C%EF%BD%9C%E8%B2%A1%E6%94%BF%E5%A7%94%E5%93%A1%E6%9C%83%EF%BD%9C%E5%85%AC%E8%A6%96%E7%8D%A8%E7%AB%8B%E6%80%A7%E3%80%81%E8%8F%AF%E8%A6%96%E8%99%A7%E6%90%8D.pdf","title":"財政委員會","body":"20160512｜黃國昌｜財政委員會｜公視獨立性、華視虧損"},{"style":"style6","imagePath":"images/31.jpg","pdfPath":"pdf/20160504%EF%BD%9C%E9%BB%83%E5%9C%8B%E6%98%8C%EF%BD%9C%E8%B2%A1%E6%94%BF%E5%A7%94%E5%93%A1%E6%9C%83%EF%BD%9C%E8%A3%81%E6%92%A4%E9%80%80%E8%BC%94%E6%9C%83.pdf","title":"財政委員會","body":"20160504｜黃國昌｜財政委員會｜裁撤退輔會"},{"style":"style2","imagePath":"images/30.jpg","pdfPath":"pdf/20160502%EF%BD%9C%E9%BB%83%E5%9C%8B%E6%98%8C%EF%BD%9C%E6%95%99%E8%82%B2%E5%8F%8A%E6%96%87%E5%8C%96%E5%A7%94%E5%93%A1%E6%9C%83%EF%BD%9C%E5%BE%AE%E8%AA%BF%E8%AA%B2%E7%B6%B1.pdf","title":"教育及文化委員會","body":"20160502｜黃國昌｜教育及文化委員會｜微調課綱"},{"style":"style3","imagePath":"images/29.jpg","pdfPath":"pdf/20160428%EF%BD%9C%E9%BB%83%E5%9C%8B%E6%98%8C%EF%BD%9C%E8%B2%A1%E6%94%BF%E5%A7%94%E5%93%A1%E6%9C%83%EF%BD%9C%E4%BA%BA%E6%B0%91%E5%8F%83%E8%88%87%E5%AF%A9%E5%88%A4%E7%9A%84%E6%8E%A8%E5%8B%95%E3%80%81%E6%9C%80%E9%AB%98%E6%B3%95%E9%99%A2%E6%B0%91%E4%BA%8B%E5%BA%AD%E4%B9%8F%E8%A8%80%E8%A9%9E%E8%BE%AF%E8%AB%96.pdf","title":"司法及法制委員會","body":"20160428｜黃國昌｜財政委員會｜人民參與審判的推動、最高法院民事庭乏言詞辯論"},{"style":"style1","imagePath":"images/28.jpg","pdfPath":"pdf/20160420%EF%BD%9C%E9%BB%83%E5%9C%8B%E6%98%8C%EF%BD%9C%E5%8F%B8%E6%B3%95%E5%8F%8A%E6%B3%95%E5%88%B6%E5%A7%94%E5%93%A1%E6%9C%83%EF%BD%9C%E7%A2%BA%E8%AA%8D%E6%B3%95%E5%8B%99%E9%83%A8%E6%9C%89%E7%84%A1%E9%80%9A%E7%9F%A5%E4%B8%AD%E5%9C%8B%E5%85%AC%E5%AE%89%E6%8A%93%E4%BA%BA.pdf","title":"司法及法制委員會","body":"20160420｜黃國昌｜司法及法制委員會｜確認法務部有無通知中國公安抓人"},{"style":"style5","imagePath":"images/27.jpg","pdfPath":"pdf/20160418%EF%BD%9C%E9%BB%83%E5%9C%8B%E6%98%8C%EF%BD%9C%E5%8F%B8%E6%B3%95%E5%8F%8A%E6%B3%95%E5%88%B6%E5%A7%94%E5%93%A1%E6%9C%83%EF%BD%9Cvs.%20%E7%BE%85%E7%91%A9%E9%9B%AA%E3%80%81PTT%E9%80%90%E5%AD%97%E7%A8%BF.pdf","title":"司法及法制委員會","body":"20160418｜黃國昌｜司法及法制委員會｜vs. 羅瑩雪、PTT逐字稿"},{"style":"style6","imagePath":"images/26.jpg","pdfPath":"pdf/20160418%EF%BD%9C%E9%BB%83%E5%9C%8B%E6%98%8C%EF%BD%9C%E5%8F%B8%E6%B3%95%E5%8F%8A%E6%B3%95%E5%88%B6%E5%A7%94%E5%93%A1%E6%9C%83%EF%BD%9Cvs.%20%E7%BE%85%E7%91%A9%E9%9B%AA%E3%80%81%E6%B3%95%E5%AD%B8%E6%95%99%E5%AE%A4.pdf","title":"司法及法制委員會","body":"20160418｜黃國昌｜司法及法制委員會｜vs. 羅瑩雪、法學教室"},{"style":"style4","imagePath":"images/25.jpg","pdfPath":"pdf/20160414%EF%BD%9C%E9%BB%83%E5%9C%8B%E6%98%8C%EF%BD%9C%E5%85%A7%E6%94%BF%E5%A7%94%E5%93%A1%E6%9C%83%EF%BD%9C%E8%8F%B2%E5%BE%8B%E8%B3%93%E4%BA%8B%E4%BB%B6.pdf","title":"內政委員會","body":"20160414｜黃國昌｜內政委員會｜菲律賓事件"},{"style":"style1","imagePath":"images/24.jpg","pdfPath":"pdf/20160414%EF%BD%9C%E9%BB%83%E5%9C%8B%E6%98%8C%EF%BD%9C%E5%8F%B8%E6%B3%95%E5%8F%8A%E6%B3%95%E5%88%B6%E5%A7%94%E5%93%A1%E6%9C%83%EF%BD%9C%E8%8F%B2%E5%BE%8B%E8%B3%93%E4%BA%8B%E4%BB%B6%E3%80%81%E5%B7%B4%E6%8B%BF%E9%A6%AC%E4%BA%8B%E4%BB%B6(vs.%E7%BE%85%E7%91%A9%E9%9B%AA).pdf","title":"司法及法制委員會","body":"20160414｜黃國昌｜司法及法制委員會｜菲律賓事件、巴拿馬事件(vs.羅瑩雪)"},{"style":"style2","imagePath":"images/23.jpg","pdfPath":"pdf/20160413%EF%BD%9C%E9%BB%83%E5%9C%8B%E6%98%8C%EF%BD%9C%E5%85%A7%E6%94%BF%E5%A7%94%E5%93%A1%E6%9C%83%EF%BD%9C%E8%82%AF%E4%BA%9E%E6%A1%88%E3%80%81%E6%B3%95%E5%8B%99%E9%83%A8%E9%80%9A%E5%A0%B1%E4%B8%AD%E5%9C%8B%E6%8A%93%E4%BA%BA.pdf","title":"內政委員會","body":"20160413｜黃國昌｜內政委員會｜肯亞案、法務部通報中國抓人"},{"style":"style3","imagePath":"images/22.jpg","pdfPath":"pdf/20160411%EF%BD%9C%E9%BB%83%E5%9C%8B%E6%98%8C%EF%BD%9C%E8%B2%A1%E6%94%BF%E5%A7%94%E5%93%A1%E6%9C%83%EF%BD%9C%E8%87%BA%E7%81%A3%E4%BA%BA%E8%A2%AB%E9%81%A3%E9%80%81%E5%88%B0%E4%B8%AD%E5%9C%8B%E3%80%81%E8%87%BA%E7%81%A3%E7%9C%81%E6%94%BF%E5%BA%9C%E5%86%97%E5%93%A1%E3%80%81%E6%B6%88%E9%98%B2%E5%93%A1%E9%80%B2%E7%94%A8%E4%B8%8D%E8%B6%B3.pdf","title":"財政委員會","body":"20160411｜黃國昌｜財政委員會｜臺灣人被遣送到中國、臺灣省政府冗員、消防員進用不足"},{"style":"style4","imagePath":"images/21.jpg","pdfPath":"pdf/20160407%EF%BD%9C%E9%BB%83%E5%9C%8B%E6%98%8C%EF%BD%9C%E8%B2%A1%E6%94%BF%E5%A7%94%E5%93%A1%E6%9C%83%EF%BD%9C%E7%A8%85%E5%8B%99%E4%BA%BA%E5%93%A1%E7%8D%8E%E5%8B%B5%E9%87%91%E3%80%81%E9%81%A0%E9%9B%84%E9%86%AB%E9%99%A2%E6%89%BF%E7%A7%9F%E5%9C%8B%E6%9C%89%E5%9C%B0%E3%80%81%E6%B5%B7%E5%A4%96%E9%81%BF%E7%A8%85%E6%A2%9D%E6%AC%BE.pdf","title":"財政委員會","body":"20160407｜黃國昌｜財政委員會｜ 稅務人員獎勵金、遠雄醫院承租國有地、海外避稅條款"},{"style":"style5","imagePath":"images/20.jpg","pdfPath":"pdf/20160407%EF%BD%9C%E9%BB%83%E5%9C%8B%E6%98%8C%EF%BD%9C%E5%8F%B8%E6%B3%95%E5%8F%8A%E6%B3%95%E5%88%B6%E5%A7%94%E5%93%A1%E6%9C%83%EF%BD%9C%E8%BE%B2%E7%94%B0%E6%B0%B4%E5%88%A9%E6%9C%83%E7%A7%81%E4%BA%BA%E4%BB%BB%E7%94%A8%E3%80%81%E6%B1%90%E6%AD%A2%E9%87%91%E9%BE%8D%E6%B9%96%E7%B6%AD%E8%AD%B7.pdf","title":"司法及法制委員會","body":"20160407｜黃國昌｜司法及法制委員會｜農田水利會私人任用、汐止金龍湖維護"},{"style":"style6","imagePath":"images/19.jpg","pdfPath":"pdf/20160406%EF%BD%9C%E9%BB%83%E5%9C%8B%E6%98%8C%EF%BD%9C%E8%B2%A1%E6%94%BF%E5%A7%94%E5%93%A1%E6%9C%83%EF%BD%9C%E8%B3%AA%E8%A9%A2%E8%B2%A1%E6%94%BF%E9%83%A8%E9%95%B7%20%E5%8F%8D%E6%B5%B7%E5%A4%96%E9%81%BF%E7%A8%85%E6%A2%9D%E6%AC%BE.pdf","title":"財政委員會","body":"20160406｜黃國昌｜財政委員會｜質詢財政部長 反海外避稅條款"},{"style":"style2","imagePath":"images/18.jpg","pdfPath":"pdf/20160331%EF%BD%9C%E9%BB%83%E5%9C%8B%E6%98%8C%EF%BD%9C%E5%85%A7%E6%94%BF%E5%A7%94%E5%93%A1%E6%9C%83%EF%BD%9C%E9%9A%A8%E6%A9%9F%E6%AE%BA%E4%BA%BA%E4%BA%8B%E4%BB%B6%E8%99%95%E7%90%86%E5%8F%8A%E9%A0%90%E9%98%B2%E5%B0%8D%E7%AD%96.pdf","title":"內政委員會","body":"20160331｜黃國昌｜內政委員會｜隨機殺人事件處理及預防對策"},{"style":"style3","imagePath":"images/17.jpg","pdfPath":"pdf/20160330%EF%BD%9C%E9%BB%83%E5%9C%8B%E6%98%8C%EF%BD%9C%E8%B2%A1%E6%94%BF%E5%A7%94%E5%93%A1%E6%9C%83%EF%BD%9C%E8%A8%AD%E7%BD%AE%E5%8B%9E%E5%B7%A5%E8%91%A3%E4%BA%8B%20%E8%8E%AB%E5%BF%98%E5%8B%9E%E5%B7%A5%E5%BF%83%E8%81%B2.pdf","title":"財政委員會","body":"20160330｜黃國昌｜財政委員會｜設置勞工董事 莫忘勞工心聲"},{"style":"style1","imagePath":"images/16.jpg","pdfPath":"pdf/20160328%EF%BD%9C%E9%BB%83%E5%9C%8B%E6%98%8C%EF%BD%9C%E8%B2%A1%E6%94%BF%E5%A7%94%E5%93%A1%E6%9C%83%EF%BD%9C%E9%87%91%E7%AE%A1%E6%9C%83%E5%A0%B1%E5%91%8ATRF%E6%90%8D%E5%A4%B1%E9%87%91%E9%A1%8D%E8%88%87%E8%99%95%E7%90%86%E6%96%B9%E5%BC%8F.pdf","title":"財政委員會","body":"20160328｜黃國昌｜財政委員會｜金管會報告TRF損失金額與處理方式"},{"style":"style5","imagePath":"images/15.jpg","pdfPath":"pdf/20160323%EF%BD%9C%E9%BB%83%E5%9C%8B%E6%98%8C%EF%BD%9C%E7%B6%93%E6%BF%9F%E5%A7%94%E5%93%A1%E6%9C%83%EF%BD%9C%E6%A0%B8%E7%87%83%E6%96%99%E6%A3%92%E6%B1%BA%E5%AE%9A%E7%8F%BE%E5%9C%B0%E4%B9%BE%E5%BC%8F%E5%84%B2%E5%AD%98%E7%A8%8B%E5%BA%8F%E7%82%BA%E4%BD%95%EF%BC%9F.pdf","title":"經濟委員會","body":"20160323｜黃國昌｜經濟委員會｜核燃料棒決定現地乾式儲存程序為何？"},{"style":"style6","imagePath":"images/14.jpg","pdfPath":"pdf/20160323%EF%BD%9C%E9%BB%83%E5%9C%8B%E6%98%8C%EF%BD%9C%E8%B2%A1%E6%94%BF%E5%A7%94%E5%93%A1%E6%9C%83%EF%BD%9C%E4%BF%9D%E9%9A%9C%E8%BA%AB%E5%BF%83%E9%9A%9C%E7%A4%99%E8%80%85%E4%B9%8B%E5%B7%A5%E4%BD%9C%E6%AC%8A%EF%BC%8C%E7%94%B1%E8%A8%98%E5%B8%B3%E5%A3%AB%E6%B3%95%E5%87%BA%E7%99%BC%EF%BC%81.pdf","title":"財政委員會","body":"20160323｜黃國昌｜財政委員會｜保障身心障礙者之工作權，由記帳士法出發！ "},{"style":"style4","imagePath":"images/13.jpg","pdfPath":"pdf/20160321%EF%BD%9C%E9%BB%83%E5%9C%8B%E6%98%8C%EF%BD%9C%E5%8F%B8%E6%B3%95%E5%8F%8A%E6%B3%95%E5%88%B6%E5%A7%94%E5%93%A1%E6%9C%83%EF%BD%9C%E8%B3%87%E7%AD%96%E6%9C%83%E6%8A%80%E6%9C%8D%E4%B8%AD%E5%BF%83%E4%BA%BA%E5%93%A1%E7%A7%BB%E8%BD%89.pdf","title":"司法及法制委員會","body":"20160321｜黃國昌｜司法及法制委員會｜資策會技服中心人員移轉"},{"style":"style1","imagePath":"images/12.jpg","pdfPath":"pdf/20160321%EF%BD%9C%E9%BB%83%E5%9C%8B%E6%98%8C%EF%BD%9C%E8%B2%A1%E6%94%BF%E5%A7%94%E5%93%A1%E6%9C%83%EF%BD%9C%E5%AF%A9%E6%9F%A5%E3%80%8C%E7%B8%BD%E9%A0%90%E7%AE%97%E7%AC%AC%E4%BA%8C%E9%A0%90%E5%82%99%E9%87%91%E5%8B%95%E6%94%AF%E6%95%B8%E9%A1%8D%E8%A1%A8%E3%80%8D%E7%AD%8914%E6%A1%88.pdf","title":"財政委員會","body":"20160321｜黃國昌｜財政委員會｜審查「總預算第二預備金動支數額表」等14案"},{"style":"style2","imagePath":"images/11.jpg","pdfPath":"pdf/20160317%EF%BD%9C%E9%BB%83%E5%9C%8B%E6%98%8C%EF%BD%9C%E8%B2%A1%E6%94%BF%E5%A7%94%E5%93%A1%E6%9C%83%EF%BD%9C%E3%80%8C%E4%BF%9D%E9%9A%AA%E6%B3%95%E7%AC%AC%E4%B8%80%E7%99%BE%E9%9B%B6%E4%B8%83%E6%A2%9D%E6%A2%9D%E6%96%87%E4%BF%AE%E6%AD%A3%E8%8D%89%E6%A1%88%E3%80%8D.pdf","title":"財政委員會","body":"20160317｜黃國昌｜財政委員會｜「保險法第一百零七條條文修正草案」"},{"style":"style3","imagePath":"images/10.jpg","pdfPath":"pdf/20160317%EF%BD%9C%E9%BB%83%E5%9C%8B%E6%98%8C%EF%BD%9C%E5%85%A7%E6%94%BF%E5%A7%94%E5%93%A1%E6%9C%83%EF%BD%9C%E5%AF%A9%E6%9F%A5%E8%A1%8C%E6%94%BF%E9%99%A2%E5%87%BD%E8%AB%8B%E5%AF%A9%E8%AD%B0%E3%80%8C%E9%9B%86%E6%9C%83%E9%81%8A%E8%A1%8C%E6%B3%95%E4%BF%AE%E6%AD%A3%E8%8D%89%E6%A1%88%E3%80%8D%E6%A1%88.pdf","title":"內政委員會","body":"20160317｜黃國昌｜內政委員會｜審查行政院函請審議「集會遊行法修正草案」"},{"style":"style4","imagePath":"images/9.jpg","pdfPath":"pdf/20160316%EF%BD%9C%E9%BB%83%E5%9C%8B%E6%98%8C%EF%BD%9C%E8%B2%A1%E6%94%BF%E5%A7%94%E5%93%A1%E6%9C%83%EF%BD%9C%E9%81%BA%E7%94%A2%E7%A8%85%E5%8E%BB%E5%93%AA%E4%BA%86%EF%BC%9F.pdf","title":"財政委員會","body":"20160316｜黃國昌｜財政委員會｜遺產稅去哪了？"},{"style":"style5","imagePath":"images/8.jpg","pdfPath":"pdf/20160316｜黃國昌｜財政委員會質詢｜遺產稅去哪了？.pdf","title":"內政委員會","body":"20160316｜黃國昌｜內政委員會｜罷免宣傳遭裁罰"},{"style":"style6","imagePath":"images/7.jpg","pdfPath":"pdf/20160314%EF%BD%9C%E9%BB%83%E5%9C%8B%E6%98%8C%EF%BD%9C%E8%B2%A1%E6%94%BF%E5%A7%94%E5%93%A1%E6%9C%83%EF%BD%9C%E7%B5%B1%E8%A8%88%E6%95%B8%E5%AD%97%E4%B8%8D%E6%87%89%E7%B2%89%E9%A3%BE%E5%A4%AA%E5%B9%B3%20%E7%B2%BE%E7%A2%BA%E9%80%8F%E6%98%8E%E6%89%8D%E5%85%B7%E5%8F%83%E8%80%83%E5%83%B9%E5%80%BC.pdf","title":"財政委員會","body":"20160314｜黃國昌｜財政委員會｜統計數字不應粉飾太平 精確透明才具參考價值"},{"style":"style2","imagePath":"images/6.jpg","pdfPath":"pdf/20160314%EF%BD%9C%E9%BB%83%E5%9C%8B%E6%98%8C%EF%BD%9C%E5%85%A7%E6%94%BF%E5%A7%94%E5%93%A1%E6%9C%83%EF%BD%9C%E8%B3%AA%E8%A9%A2%E4%B8%8D%E7%95%B6%E9%BB%A8%E7%94%A2.pdf","title":"內政委員會","body":"20160314｜黃國昌｜內政委員會｜質詢不當黨產"},{"style":"style3","imagePath":"images/5.jpg","pdfPath":"pdf/20160310%EF%BD%9C%E9%BB%83%E5%9C%8B%E6%98%8C%EF%BD%9C%E8%B2%A1%E6%94%BF%E5%A7%94%E5%93%A1%E6%9C%83%EF%BD%9C%E5%B0%8D%E4%B8%AD%E5%A4%AE%E9%8A%80%E8%A1%8C%E6%A5%AD%E5%8B%99%E5%A0%B1%E5%91%8A%E6%8F%90%E5%87%BA%E8%B3%AA%E8%A9%A2%20.pdf","title":"財政委員會","body":"20160310｜黃國昌｜財政委員會｜對中央銀行業務報告提出質詢"},{"style":"style1","imagePath":"images/4.jpg","pdfPath":"pdf/20160309%EF%BD%9C%E9%BB%83%E5%9C%8B%E6%98%8C%EF%BD%9C%E4%BA%A4%E9%80%9A%E5%A7%94%E5%93%A1%E6%9C%83%EF%BD%9C%E8%BF%91%E4%BE%86%E5%AA%92%E9%AB%94%E4%BD%B5%E8%B3%BC%E6%A1%88%E5%8F%8A%E5%8F%8D%E5%AA%92%E9%AB%94%E5%A3%9F%E6%96%B7%E4%BA%8B%E9%A0%85%E5%A0%B1%E5%91%8A.pdf","title":"交通委員會","body":"20160309｜黃國昌｜交通委員會｜近來媒體併購案及反媒體壟斷事項報告"},{"style":"style5","imagePath":"images/3.jpg","pdfPath":"pdf/20160309%EF%BD%9C%E9%BB%83%E5%9C%8B%E6%98%8C%EF%BD%9C%E8%B2%A1%E6%94%BF%E5%A7%94%E5%93%A1%E6%9C%83%EF%BD%9C%E8%B3%AA%E8%A9%A2%E8%B2%A1%E6%94%BF%E9%83%A8%E9%95%B7%E6%9C%89%E9%97%9C%E7%A7%9F%E7%A8%85%E6%94%B9%E9%9D%A9.pdf","title":"財政委員會","body":"20160309｜黃國昌｜財政委員會｜質詢財政部長有關租稅改革"},{"style":"style6","imagePath":"images/2.jpg","pdfPath":"pdf/20160307%EF%BD%9C%E9%BB%83%E5%9C%8B%E6%98%8C%EF%BD%9C%E8%B2%A1%E6%94%BF%E5%A7%94%E5%93%A1%E6%9C%83%EF%BD%9C%E8%B3%AA%E8%A9%A2%E9%87%91%E7%AE%A1%E6%9C%83%E4%BA%BA%E6%B0%91%E5%B9%A3%E8%A1%8D%E7%94%9F%E6%80%A7%E9%87%91%E8%9E%8D%E5%95%86%E5%93%81TRF&DKO.pdf","title":"財政委員會","body":"20160307｜黃國昌｜財政委員會｜質詢金管會人民幣衍生性金融商品TRF&amp;DKO"},{"style":"style4","imagePath":"images/1.jpg","pdfPath":"pdf/20160219%EF%BD%9C%E9%BB%83%E5%9C%8B%E6%98%8C%EF%BD%9C%E9%99%A2%E6%9C%83%EF%BD%9C%20%E7%AB%8B%E9%99%A2%E9%96%8B%E8%AD%B0%E7%AC%AC%E4%B8%80%E5%A4%A9%E7%B8%BD%E8%B3%AA%E8%A9%A2.pdf","title":"院會","body":"20160219｜黃國昌｜院會｜立院開議第一天總質詢"}]
